ai_lang/__init__.py
ai_lang/ai_lang.py
ai_lang/cli.py
ai_lang-0.0.6.dist-info/LICENSE
ai_lang-0.0.6.dist-info/METADATA
ai_lang-0.0.6.dist-info/WHEEL
ai_lang-0.0.6.dist-info/entry_points.txt
ai_lang-0.0.6.dist-info/RECORD
