Metadata-Version: 2.1
Name: ai-lang
Version: 0.0.6
Summary: DotAI - Natural Language Programming Language
Home-page: https://github.com/The-Swarm-Corporation/.ai
License: MIT
Keywords: artificial intelligence,deep learning,natural language processing,prompt engineering
Author: Kye Gomez
Author-email: kye@apac.ai
Requires-Python: >=3.10,<4.0
Classifier: Development Status :: 4 - Beta
Classifier: Intended Audience :: Developers
Classifier: License :: OSI Approved :: MIT License
Classifier: Programming Language :: Python :: 3
Classifier: Programming Language :: Python :: 3.10
Classifier: Programming Language :: Python :: 3.11
Classifier: Programming Language :: Python :: 3.12
Classifier: Programming Language :: Python :: 3.9
Classifier: Topic :: Scientific/Engineering :: Artificial Intelligence
Requires-Dist: loguru
Requires-Dist: python-dotenv
Requires-Dist: swarms
Project-URL: Documentation, https://github.com/The-Swarm-Corporation/.ai
Project-URL: Repository, https://github.com/The-Swarm-Corporation/.ai
